<DataSets xmlns="http://www.tdwg.org/schemas/abcd/2.06">
  <DataSet>
    <TechnicalContacts>
      <TechnicalContact preferred="false">
        <Name>ich</Name>
      </TechnicalContact>
    </TechnicalContacts>
    <ContentContacts>
      <ContentContact preferred="false">
        <Name>ich</Name>
      </ContentContact>
    </ContentContacts>
    <Metadata>
      <Description>
        <Representation language="en">
          <Title>trash</Title>
        </Representation>
      </Description>
      <Owners>
        <Owner>
          <Person>
            <FullName>ich</FullName>
          </Person>
        </Owner>
      </Owners>
    </Metadata>
    <Units>
      <Unit>
        <SourceInstitutionID>1</SourceInstitutionID>
        <SourceID>2</SourceID>
        <UnitID>3</UnitID>
      </Unit>
    </Units>
  </DataSet>
</DataSets>